PYCDef/__init__.py
PYCDef/_float.py
PYCDef/_int.py
PYCDef/_pyctyerror.py
PYCDef/_type.py
PYCDef/array.py
PYCDef/char.py
PYCDef/ext.py
PyCty-1.3.0.dist-info/LICENCE
PyCty-1.3.0.dist-info/METADATA
PyCty-1.3.0.dist-info/WHEEL
PyCty-1.3.0.dist-info/top_level.txt
PyCty-1.3.0.dist-info/RECORD
