Metadata-Version: 2.1
Name: PyCty
Version: 1.3.0
Summary: Python C Types
Home-page: UNKNOWN
Author: Harsha Addanki
Author-email: harsha7addanki@gmail.com
License: UNKNOWN
Platform: UNKNOWN
Classifier: Programming Language :: Python :: 3
Classifier: License :: OSI Approved :: MIT License
Classifier: Operating System :: OS Independent
Requires-Python: >=3.8.5
